{"name":"Scrollimated","tagline":"","body":"![Picture](http://www.creacionesindiscriminadas.com/wp-content/themes/creaIndis/img/logo.png)\r\n\r\n#Scrollimated\r\n\r\nAnimate visual elements to construct a composition in a puzzle way while scrolling (works better if the composition is not on top of the page).\r\n\r\n##Configuration\r\n\r\n###index.html\r\n- .scrollimated (_required_): container of the composition\r\n- data-scrollimated-transition (_required for animated elements_): data attribute used to define the direction of the motion. Elements without this data attribute remain fixed. Accepted values: top, bottom, left, right, topLeft, topRight, bottomLeft, bottomRight \r\n- data-scrollimated-delay: defines where the animation starts for the element\r\n\r\n###script.js\r\n- actionRadio:\tdefines the part of the window with the elements blocked in place\r\n- spread: defines the quantity of motion\r\n- duration: controls motion speed\r\n\r\n###styles.css\r\nSizing values defined in percent to keep it responsive.\r\n\r\nIt's recommanded to do it with positionning too (but not required).","google":"","note":"Don't delete this file! It's used internally to help with page regeneration."}